gritholdings/__init__.py
gritholdings/browser_automation.py
gritholdings/gmail.py
gritholdings/helpers.py
gritholdings/llm.py
gritholdings/local_db.py
gritholdings/session.py
gritholdings-1.1.3.dist-info/METADATA
gritholdings-1.1.3.dist-info/WHEEL
gritholdings-1.1.3.dist-info/top_level.txt
gritholdings-1.1.3.dist-info/RECORD
