Metadata-Version: 2.1
Name: gritholdings
Version: 1.1.3
Summary: The Grit Holdings SDK for Python
Home-page: https://github.com/gritholdings/gritholdings-sdk-py
Author: Grit Holdings, Inc
License: Apache License 2.0
Project-URL: Documentation, https://gritholdings.gitbook.io/
Project-URL: Source, https://github.com/gritholdings/gritholdings-sdk-py
Classifier: Development Status :: 5 - Production/Stable
Classifier: Intended Audience :: Developers
Classifier: Natural Language :: English
Classifier: License :: OSI Approved :: Apache Software License
Classifier: Programming Language :: Python :: 3
Requires-Python: >= 3.8
Requires-Dist: selenium>=4.0.0
Requires-Dist: openai>=1.0.0
Requires-Dist: anthropic>=0.26.0
Requires-Dist: google-api-python-client>=1.12.8
Requires-Dist: google>=3.0.0
Requires-Dist: gspread>=3.6.0
